logpunch/__init__.py
logpunch/customexception.py
logpunch/customlogger.py
logpunch-1.0.2.dist-info/licenses/LICENSE
logpunch-1.0.2.dist-info/METADATA
logpunch-1.0.2.dist-info/WHEEL
logpunch-1.0.2.dist-info/top_level.txt
logpunch-1.0.2.dist-info/RECORD
