Metadata-Version: 2.4
Name: logpunch
Version: 1.0.2
Summary: Logpunch is a lightweight Python package providing a customizable colored logger and enhanced exception handling with detailed error tracking — designed to streamline logging and debugging in data science and machine learning projects.
Home-page: https://github.com/gauravgulia26/logpunch
Author: Gourav Gulia
Author-email: Gourav Gulia <grvgulia007@gmail.com>
License: MIT
Keywords: logging,logger,exception,data-science,machine-learning
Requires-Python: >=3.7
License-File: LICENSE
Requires-Dist: pydantic
Requires-Dist: colorama
Dynamic: license-file
